libcalab_ogre3d/MotionGraph.py
libcalab_ogre3d/Plugin_ParticleFX.4.0.dylib
libcalab_ogre3d/Plugin_ParticleFX2.4.0.dylib
libcalab_ogre3d/RenderSystem_Metal.4.0.dylib
libcalab_ogre3d/RenderSystem_NULL.4.0.dylib
libcalab_ogre3d/__init__.py
libcalab_ogre3d/config.py
libcalab_ogre3d/controlmodule.py
libcalab_ogre3d/default_settings.py
libcalab_ogre3d/filechooser.py
libcalab_ogre3d/filechooser_mac.py
libcalab_ogre3d/filechooser_wx.py
libcalab_ogre3d/libBaseLib.dylib
libcalab_ogre3d/libClassificationLib.dylib
libcalab_ogre3d/libMainLib.dylib
libcalab_ogre3d/libOIS.1.5.0.dylib
libcalab_ogre3d/libOgreNextAtmosphere.4.0.dylib
libcalab_ogre3d/libOgreNextHlmsPbs.4.0.dylib
libcalab_ogre3d/libOgreNextHlmsUnlit.4.0.dylib
libcalab_ogre3d/libOgreNextImgui.4.0.dylib
libcalab_ogre3d/libOgreNextMain.4.0.dylib
libcalab_ogre3d/libOgreNextMeshLodGenerator.4.0.dylib
libcalab_ogre3d/libOgreNextOverlay.4.0.dylib
libcalab_ogre3d/libOgreNextProperty.4.0.dylib
libcalab_ogre3d/libOgreNextSceneFormat.4.0.dylib
libcalab_ogre3d/libPhysicsLib.dylib
libcalab_ogre3d/libann.dylib
libcalab_ogre3d/libfltk.1.4.dylib
libcalab_ogre3d/libfltk_forms.1.4.dylib
libcalab_ogre3d/libfltk_gl.1.4.dylib
libcalab_ogre3d/libfltk_images.1.4.dylib
libcalab_ogre3d/libfreeimage.dylib
libcalab_ogre3d/liblibmainlib_console.so
libcalab_ogre3d/liblua51.dylib
libcalab_ogre3d/libmainlib.cpython-312-darwin.so
libcalab_ogre3d/libqpOASES.dylib
libcalab_ogre3d/luamodule.py
libcalab_ogre3d/readline.so
libcalab_ogre3d/rendermodule.py
libcalab_ogre3d/test_sample_python.py
libcalab_ogre3d/Resource/ogreconfig.txt
libcalab_ogre3d/Resource/ogreconfig_linux.txt
libcalab_ogre3d/Resource/ogreconfig_linux12.txt
libcalab_ogre3d/Resource/ogreconfig_linux_highquality_sepwin.txt
libcalab_ogre3d/Resource/ogreconfig_linux_sepwin.txt
libcalab_ogre3d/Resource/ogreconfig_mac.txt
libcalab_ogre3d/Resource/resources3_relative.cfg
libcalab_ogre3d/Resource/viewpoint.txt
libcalab_ogre3d/Resource/default/colormap.bmp
libcalab_ogre3d-0.1.6.dist-info/METADATA
libcalab_ogre3d-0.1.6.dist-info/WHEEL
libcalab_ogre3d-0.1.6.dist-info/top_level.txt
libcalab_ogre3d-0.1.6.dist-info/RECORD
